[
    {
        "owner": "suda",
        "name": "dvsync",
        "contributors": 3,
        "issues": 0,
        "stars": 55,
        "forks": 4,
        "languages": {
            "Shell": 100.0
        },
        "tags": [
            "docker",
            "kubernetes",
            "tunnel",
            "containers"
        ],
        "moreLink": ""
    },
    {
        "owner": "PyCQA",
        "name": "pydocstyle",
        "contributors": 75,
        "issues": 82,
        "stars": 849,
        "forks": 159,
        "languages": {
            "Python": 100.0
        },
        "tags": [
            "python",
            "linter",
            "docstrings"
        ],
        "moreLink": "https://github.com/PyCQA/pydocstyle/issues/575"
    },
    {
        "owner": "amacneil",
        "name": "dbmate",
        "contributors": 24,
        "issues": 33,
        "stars": 2335,
        "forks": 160,
        "languages": {
            "Go": 98.5,
            "Other": 1.5
        },
        "tags": [
            "nodejs",
            "mysql",
            "python",
            "docker",
            "golang",
            "migrations",
            "sqlite",
            "postgresql",
            "migration",
            "database-migrations",
            "database-schema"
        ],
        "moreLink": "https://github.com/amacneil/dbmate/issues/258"
    },
    {
        "owner": "SentryPeer",
        "name": "SentryPeer",
        "contributors": 4,
        "issues": 3,
        "stars": 58,
        "forks": 7,
        "languages": {
            "C": 70.4,
            "JavaScript": 9.3,
            "Vue": 4.3,
            "Perl": 4.0,
            "M4": 3.3,
            "Makefile": 2.1,
            "Other": 6.6
        },
        "tags": [
            "security",
            "machine-learning",
            "sip",
            "honeypot",
            "peer-to-peer",
            "geolocation",
            "p2p",
            "software-engineering",
            "voip",
            "fraud-prevention",
            "phonenumber",
            "telecommunications",
            "fraud-detection",
            "security-tools",
            "chaos-engineering",
            "fraud",
            "telecoms-intelligence"
        ],
        "moreLink": "https://github.com/SentryPeer/SentryPeer/issues/1"
    }
]